eth_contract/__init__.py
eth_contract/contract.py
eth_contract/create2.py
eth_contract/create3.py
eth_contract/deploy_utils.py
eth_contract/entrypoint.py
eth_contract/erc20.py
eth_contract/history_storage.py
eth_contract/human.py
eth_contract/multicall3.py
eth_contract/slots.py
eth_contract/utils.py
eth_contract/weth.py
eth_contract/abis/createx.json
eth_contract/abis/erc20.json
eth_contract/abis/multicall3.json
eth_contract/abis/weth.json
eth_contract/deployments/EntryPoint07.json
eth_contract/deployments/EntryPoint08.json
eth_contract/deployments/WETH9.json
eth_contract/txs/create2.tx
eth_contract/txs/createx.tx
eth_contract/txs/multicall3.tx
eth_contract-0.3.0.dist-info/licenses/LICENSE
eth_contract-0.3.0.dist-info/METADATA
eth_contract-0.3.0.dist-info/WHEEL
eth_contract-0.3.0.dist-info/top_level.txt
eth_contract-0.3.0.dist-info/RECORD
