Metadata-Version: 2.4
Name: eth-contract
Version: 0.3.0
Summary: Add your description here
Requires-Python: >=3.9
License-File: LICENSE
Requires-Dist: web3>=7.12.0
Dynamic: license-file
